{"id":"1de2ebb1-01be-46f9-9b02-9e4b7b6c5a09","first_name":"John F","last_name":"Reed","office":"Reed, John F. (Senator)","report_date":"03/01/2019","transactions":[{"date":"02/04/2019","ticker":"XLNX","asset_name":"Xilinx, Inc.","asset_type":"Stock","order_type":"Sale (Partial)","amount":"$1,001 - $15,000"},{"date":"02/04/2019","ticker":"XLNX","asset_name":"Xilinx, Inc.","asset_type":"Stock","order_type":"Sale (Partial)","amount":"$1,001 - $15,000"},{"date":"02/04/2019","ticker":"XLNX","asset_name":"Xilinx, Inc.","asset_type":"Stock","order_type":"Sale (Partial)","amount":"$1,001 - $15,000"},{"date":"02/04/2019","ticker":"XLNX","asset_name":"Xilinx, Inc.","asset_type":"Stock","order_type":"Sale (Partial)","amount":"$1,001 - $15,000"},{"date":"02/04/2019","ticker":"XLNX","asset_name":"Xilinx, Inc.","asset_type":"Stock","order_type":"Sale (Partial)","amount":"$1,001 - $15,000"},{"date":"02/04/2019","ticker":"XLNX","asset_name":"Xilinx, Inc.","asset_type":"Stock","order_type":"Sale (Partial)","amount":"$1,001 - $15,000"},{"date":"02/04/2019","ticker":"XLNX","asset_name":"Xilinx, Inc.","asset_type":"Stock","order_type":"Sale (Partial)","amount":"$1,001 - $15,000"},{"date":"02/04/2019","ticker":"XLNX","asset_name":"Xilinx, Inc.","asset_type":"Stock","order_type":"Sale (Partial)","amount":"$1,001 - $15,000"},{"date":"02/04/2019","ticker":"XLNX","asset_name":"Xilinx, Inc.","asset_type":"Stock","order_type":"Sale (Partial)","amount":"$1,001 - $15,000"},{"date":"02/04/2019","ticker":"XLNX","asset_name":"Xilinx, Inc.","asset_type":"Stock","order_type":"Sale (Partial)","amount":"$1,001 - $15,000"},{"date":"02/04/2019","ticker":"XLNX","asset_name":"Xilinx, Inc.","asset_type":"Stock","order_type":"Sale (Partial)","amount":"$1,001 - $15,000"},{"date":"02/04/2019","ticker":"XLNX","asset_name":"Xilinx, Inc.","asset_type":"Stock","order_type":"Sale (Partial)","amount":"$1,001 - $15,000"},{"date":"02/04/2019","ticker":"XLNX","asset_name":"Xilinx, Inc.","asset_type":"Stock","order_type":"Sale (Partial)","amount":"$1,001 - $15,000"},{"date":"02/04/2019","ticker":"XLNX","asset_name":"Xilinx, Inc.","asset_type":"Stock","order_type":"Sale (Partial)","amount":"$1,001 - $15,000"},{"date":"02/04/2019","ticker":"XLNX","asset_name":"Xilinx, Inc.","asset_type":"Stock","order_type":"Sale (Partial)","amount":"$1,001 - $15,000"},{"date":"02/04/2019","ticker":"XLNX","asset_name":"Xilinx, Inc.","asset_type":"Stock","order_type":"Sale (Partial)","amount":"$1,001 - $15,000"}]}