{"id":"33ee814c-5aef-4c2c-9ba1-245dfd145ef4","first_name":"Pat","last_name":"Roberts","office":"Roberts, Pat (Senator)","report_date":"05/17/2017","transactions":[{"date":"07/27/2015","ticker":"BIDU","asset_name":"Baidu, Inc. (NASDAQ)","asset_type":"Stock","order_type":"Purchase","amount":"$1,001 - $15,000"},{"date":"07/27/2015","ticker":"BIDU","asset_name":"Baidu, Inc. (NASDAQ)","asset_type":"Stock","order_type":"Purchase","amount":"$1,001 - $15,000"},{"date":"07/27/2015","ticker":"BIDU","asset_name":"Baidu, Inc. (NASDAQ)","asset_type":"Stock","order_type":"Purchase","amount":"$1,001 - $15,000"},{"date":"07/27/2015","ticker":"BIDU","asset_name":"Baidu, Inc. (NASDAQ)","asset_type":"Stock","order_type":"Purchase","amount":"$1,001 - $15,000"},{"date":"07/27/2015","ticker":"BIDU","asset_name":"Baidu, Inc. (NASDAQ)","asset_type":"Stock","order_type":"Purchase","amount":"$1,001 - $15,000"}]}