{"id":"5bbb799a-4bef-46a5-863a-eeaad0574157","first_name":"Lindsey","last_name":"Graham","office":"Graham, Lindsey (Senator)","report_date":"07/13/2022","transactions":[{"date":"06/30/2022","ticker":"VTIP","asset_name":"Vanguard Short-Term Inflation-Protected Securities","asset_type":"Stock","order_type":"Sale (Full)","amount":"$15,001 - $50,000"},{"date":"06/30/2022","ticker":"VTIP","asset_name":"Vanguard Short-Term Inflation-Protected Securities","asset_type":"Stock","order_type":"Sale (Full)","amount":"$15,001 - $50,000"},{"date":"06/30/2022","ticker":"VTIP","asset_name":"Vanguard Short-Term Inflation-Protected Securities","asset_type":"Stock","order_type":"Sale (Full)","amount":"$15,001 - $50,000"}]}