{"id":"5e64a4c2-f31a-4f7d-940a-eee2a9909e4d","first_name":"Patrick J","last_name":"Toomey","office":"Toomey, Pat (Senator)","report_date":"02/09/2017","transactions":[{"date":"01/27/2017","ticker":"VZ","asset_name":"Verizon Communications Inc.","asset_type":"Stock","order_type":"Sale (Partial)","amount":"$15,001 - $50,000"},{"date":"01/27/2017","ticker":"VZ","asset_name":"Verizon Communications Inc.","asset_type":"Stock","order_type":"Sale (Partial)","amount":"$15,001 - $50,000"},{"date":"01/27/2017","ticker":"VZ","asset_name":"Verizon Communications Inc.","asset_type":"Stock","order_type":"Sale (Partial)","amount":"$15,001 - $50,000"},{"date":"01/27/2017","ticker":"VZ","asset_name":"Verizon Communications Inc.","asset_type":"Stock","order_type":"Sale (Partial)","amount":"$15,001 - $50,000"},{"date":"01/27/2017","ticker":"VZ","asset_name":"Verizon Communications Inc.","asset_type":"Stock","order_type":"Sale (Partial)","amount":"$15,001 - $50,000"}]}