{"id":"b852990f-aa23-40ed-bcb2-95441817ba41","first_name":"Sheldon","last_name":"Whitehouse","office":"Whitehouse, Sheldon (Senator)","report_date":"03/17/2015","transactions":[{"date":"02/24/2015","ticker":"LLTC","asset_name":"Linear Technology Corporation (NASDAQ)","asset_type":"Stock","order_type":"Purchase","amount":"$1,001 - $15,000"},{"date":"02/24/2015","ticker":"LLTC","asset_name":"Linear Technology Corporation (NASDAQ)","asset_type":"Stock","order_type":"Purchase","amount":"$1,001 - $15,000"},{"date":"02/24/2015","ticker":"LLTC","asset_name":"Linear Technology Corporation (NASDAQ)","asset_type":"Stock","order_type":"Purchase","amount":"$1,001 - $15,000"},{"date":"02/24/2015","ticker":"LLTC","asset_name":"Linear Technology Corporation (NASDAQ)","asset_type":"Stock","order_type":"Purchase","amount":"$1,001 - $15,000"},{"date":"02/24/2015","ticker":"LLTC","asset_name":"Linear Technology Corporation (NASDAQ)","asset_type":"Stock","order_type":"Purchase","amount":"$1,001 - $15,000"},{"date":"02/24/2015","ticker":"LLTC","asset_name":"Linear Technology Corporation (NASDAQ)","asset_type":"Stock","order_type":"Purchase","amount":"$1,001 - $15,000"},{"date":"02/24/2015","ticker":"LLTC","asset_name":"Linear Technology Corporation (NASDAQ)","asset_type":"Stock","order_type":"Purchase","amount":"$1,001 - $15,000"},{"date":"02/24/2015","ticker":"LLTC","asset_name":"Linear Technology Corporation (NASDAQ)","asset_type":"Stock","order_type":"Purchase","amount":"$1,001 - $15,000"},{"date":"02/24/2015","ticker":"LLTC","asset_name":"Linear Technology Corporation (NASDAQ)","asset_type":"Stock","order_type":"Purchase","amount":"$1,001 - $15,000"},{"date":"02/24/2015","ticker":"LLTC","asset_name":"Linear Technology Corporation (NASDAQ)","asset_type":"Stock","order_type":"Purchase","amount":"$1,001 - $15,000"},{"date":"02/24/2015","ticker":"LLTC","asset_name":"Linear Technology Corporation (NASDAQ)","asset_type":"Stock","order_type":"Purchase","amount":"$1,001 - $15,000"},{"date":"02/24/2015","ticker":"LLTC","asset_name":"Linear Technology Corporation (NASDAQ)","asset_type":"Stock","order_type":"Purchase","amount":"$1,001 - $15,000"},{"date":"02/24/2015","ticker":"LLTC","asset_name":"Linear Technology Corporation (NASDAQ)","asset_type":"Stock","order_type":"Purchase","amount":"$1,001 - $15,000"}]}